AUTHORS
COPYING
ChangeLog
README.rst
requirements.txt
setup.cfg
setup.py
example/ansi.ans
example/demo.rst
example/gg.jpg
presentty/__init__.py
presentty/ansiparser.py
presentty/client.py
presentty/console.py
presentty/image.py
presentty/palette.py
presentty/presentty.py
presentty/rst.py
presentty/server.py
presentty/slide.py
presentty/text.py
presentty/transition.py
presentty.egg-info/PKG-INFO
presentty.egg-info/SOURCES.txt
presentty.egg-info/dependency_links.txt
presentty.egg-info/entry_points.txt
presentty.egg-info/not-zip-safe
presentty.egg-info/pbr.json
presentty.egg-info/requires.txt
presentty.egg-info/top_level.txt