Metadata-Version: 1.1
Name: presentty
Version: 0.1.0
Summary: Console-based presentation system
Home-page: UNKNOWN
Author: James E. Blair
Author-email: corvus@gnu.org
License: UNKNOWN
Platform: UNKNOWN
Classifier: Environment :: Console
Classifier: Intended Audience :: Developers
Classifier: Intended Audience :: Education
Classifier: Intended Audience :: End Users/Desktop
Classifier: Intended Audience :: Information Technology
Classifier: Intended Audience :: System Administrators
Classifier: License :: OSI Approved :: GNU General Public License v3 or later (GPLv3+)
Classifier: Programming Language :: Python
Classifier: Topic :: Multimedia :: Graphics :: Presentation
